{
  "generatedAt": "2026-05-26T12:13:33.255Z",
  "count": 29,
  "tickets": [
    {
      "id": "SLY-1",
      "type": "bug",
      "caseId": "savings-no-picker",
      "title": "Quick Log → Savings silently loses money",
      "surface": "save",
      "group": "savings",
      "severity": "P0",
      "kind": "confirmed",
      "summary": "When you log money as “Savings” in Quick Log, the app takes it out of your cash but never puts it into any goal — because there's no box to choose which goal it's for. So $300 leaves your balance and lands nowhere. Worse, the success toast says it worked: it reads “−$300 · Savings · — · Tap to undo”, with a dash sitting where the goal name should be.",
      "rich": {
        "mechanism": "The Quick Log modal hides the category row when you pick the “Savings” type but renders no destination (bucket/goal) picker in its place. quickLogTxn() then records a Savings-category transaction that decrements cash via the balance writer but never calls the bucket-credit path — so no goal's `saved` total moves.",
        "rootCause": "openQuickLogModal (index.html:10154-10291) has no goal-picker for type=savings; quickLogTxn (index.html:10311) records the txn through the balance delta but not through a bucket destination — so `bucket_saved_change` never fires.",
        "fix": "Add a required goal-picker to the Savings type in the Quick Log modal; block the save if no destination is chosen; route the save through `recordWithAllocation` with the chosen bucket as destination. The crediting machinery already works — the round-up path proves `bucket_saved_change` fires correctly (see log-transaction flow). This is a missing picker, not broken crediting.",
        "files": [
          "index.html:10154-10291 (openQuickLogModal — no picker)",
          "index.html:10311 (quickLogTxn)",
          "index.html:24524 (recordWithAllocation — the path it should use)"
        ],
        "evidence": {
          "flow": "darwin-A-quicklog",
          "walkDir": "2026-05-26T09-00-07",
          "steps": [
            {
              "step": "baseline",
              "action": "Dashboard on open",
              "lands": [],
              "delta": {},
              "probe": null,
              "error": null
            },
            {
              "step": "open-quicklog",
              "action": "Open Quick Log",
              "lands": [],
              "delta": {},
              "probe": null,
              "error": null
            },
            {
              "step": "select-savings",
              "action": "Select 'Savings' type",
              "lands": [],
              "delta": {},
              "probe": null,
              "error": null
            },
            {
              "step": "enter-300",
              "action": "Enter $300",
              "lands": [],
              "delta": {},
              "probe": null,
              "error": null
            },
            {
              "step": "submit",
              "action": "Submit (quickLogTxn)",
              "lands": [
                "txn_record",
                "balance_apply_delta"
              ],
              "delta": {
                "bal": "4800 → 4500",
                "txns.length": "9 → 10"
              },
              "probe": null,
              "error": null
            },
            {
              "step": "aftermath",
              "action": "Dashboard after submit",
              "lands": [],
              "delta": {},
              "probe": null,
              "error": null
            }
          ]
        }
      },
      "openBug": 11,
      "links": [
        {
          "to": "OPEN-BUGS #11",
          "why": "canonical bug record"
        }
      ]
    },
    {
      "id": "SLY-2",
      "type": "bug",
      "caseId": "bills-undo-key-mismatch",
      "title": "Bills “undo” silently no-ops — bill stuck paid, cash not returned",
      "surface": "bills",
      "group": "bills",
      "severity": "P0",
      "kind": "confirmed",
      "summary": "Pay a bill that's due before payday, then change your mind and hit undo — nothing happens. The bill stays marked paid and the money doesn't come back. It affects every bill due before payday.",
      "rich": {
        "mechanism": "Marking a pre-payday bill paid files it under NEXT month's key (a “cycle bump”, because day < payday means it belongs to the coming cycle). But the undo path looks up THIS month's key. Writer-key ≠ reader-key, so undo searches the wrong drawer, finds nothing, and quietly does nothing.",
        "rootCause": "markPaid cycle-bumps the paidBills key for day<payday bills to the next month (~index.html:25192, e.g. `2026-6-Phone Plan-10`), but undoBillPaid (index.html:8809) and unmarkBillFromCal read `paidBillKey(name,day)` = the current month (`2026-5-Phone Plan-10`). The keys never match.",
        "fix": "Make undo compute the SAME cycle-bumped key markPaid wrote (share one key-builder across mark + undo), or store the actual written key on the paidBills entry so undo reverses by stored key rather than recomputing. Pair with a regression spec asserting pay→undo restores balance + clears the flag for a pre-payday bill.",
        "files": [
          "index.html:~25192 (markPaid cycle-bump writes next-month key)",
          "index.html:8809 (undoBillPaid reads current-month key)",
          "unmarkBillFromCal (same reader-key bug)"
        ],
        "evidence": {
          "flow": "bills-mark-paid",
          "walkDir": "2026-05-26T09-00-07",
          "steps": [
            {
              "step": "baseline",
              "action": "Bills / Calendar tab",
              "lands": [],
              "delta": {},
              "probe": null,
              "error": null
            },
            {
              "step": "pay-phone",
              "action": "Pay Phone Plan now (payBillNow → BRAIN.bills.markPaid)",
              "lands": [
                "txn_record",
                "balance_apply_delta",
                "bill_mark_paid",
                "bill_mark_paid",
                "notif_add"
              ],
              "delta": {
                "bal": "4800 → 4750",
                "txns.length": "9 → 10"
              },
              "probe": null,
              "error": null
            },
            {
              "step": "after-paid",
              "action": "Calendar after pay",
              "lands": [],
              "delta": {},
              "probe": null,
              "error": null
            },
            {
              "step": "undo",
              "action": "Undo (unmarkBillFromCal — reader-key path)",
              "lands": [],
              "delta": {},
              "probe": null,
              "error": null
            },
            {
              "step": "after-undo",
              "action": "Calendar after undo",
              "lands": [],
              "delta": {},
              "probe": null,
              "error": null
            }
          ]
        }
      },
      "openBug": null,
      "links": []
    },
    {
      "id": "SLY-3",
      "type": "bug",
      "caseId": "ai-prompt-provenance",
      "title": "AI coach is fed a stale hand-written cheat-sheet (and the wrong spendable number)",
      "surface": "ai",
      "group": "ai",
      "severity": "P0",
      "kind": "confirmed",
      "summary": "The in-app AI is given a “what you know about John” brief built from hard-coded, out-of-date facts and the wrong “spendable per day” figure — so its advice rests on numbers you can't even see. There's a correct version of that brief already written in the code, but nothing calls it: the app uses a hand-maintained copy instead.",
      "rich": {
        "mechanism": "Two prompt builders exist. The correct one uses your live balance, your genuine surplus, and includes the licensed-advice disclaimer — but it has zero callers (dead code). The one actually sent to the model reads the raw stored balance and a “dynamic daily budget” (not genuine surplus), carries no disclaimer, and hard-codes facts that have drifted (a savings goal it can't find falls back to a made-up $9k; a trip date written as “June 7-15” when the real plan is August).",
        "rootCause": "buildSystemPrompt (index.html:15332 — uses getLiveBal + getGenuineSurplus + disclaimer) is dead code (0 callers). The live prompt is an inline string (index.html:15665, sent at :15766) reading raw S.bal (:15672) + getDynamicDailyBudget (:15676); it looks up goal id `rainy-day-fund` (:15649) but the intent id is `rainy-day` → miss → hard-coded $9k. Darwin hard-coded “June 7-15” (:15704) vs intent Aug 1–10.",
        "fix": "Route the live AI call through buildSystemPrompt (or replace the inline literal with it) so the prompt uses getLiveBal + getGenuineSurplus + the live intent data + the disclaimer; delete the hard-coded stale facts; fix the `rainy-day-fund`→`rainy-day` id. NOTE: on the current fixture S.bal == getLiveBal (balance divergence 0), so the raw-balance read is a structural risk here — the demonstrated harm is spend-power ($0 surplus shown as $60/day), the id-miss, the stale dates, and the missing disclaimer.",
        "files": [
          "index.html:15332 (buildSystemPrompt — correct, DEAD)",
          "index.html:15665-15743 (live inline prompt — raw S.bal, stale facts)",
          "index.html:15649 (rainy-day-fund id miss)",
          "index.html:15766 (the fetch using the inline prompt)"
        ],
        "evidence": {
          "flow": "ai-provenance",
          "walkDir": "2026-05-26T09-00-07",
          "steps": [
            {
              "step": "open-chat",
              "action": "Open AI chat",
              "lands": [],
              "delta": {},
              "probe": null,
              "error": null
            },
            {
              "step": "probe-prompt",
              "action": "Probe prompt provenance (no API key — inspect embedded numbers)",
              "lands": [],
              "delta": {},
              "probe": {
                "live_prompt_uses": "RAW S.bal (:15672) + getDynamicDailyBudget (:15676)",
                "correct_builder": "buildSystemPrompt (:15332) uses getLiveBal + getGenuineSurplus + disclaimer",
                "buildSystemPrompt_isDeadCode": "DEFINED but 0 callers (grep-confirmed)",
                "S_bal": 4800,
                "getLiveBal": 4800,
                "bal_divergence": 0,
                "getGenuineSurplus": 0,
                "getDynamicDailyBudget": 60,
                "goal_ids_present": [
                  "rainy-day"
                ],
                "rainy_lookup_byPromptId": false,
                "darwin_intent_dates": {
                  "start": "2026-08-01",
                  "end": "2026-08-10"
                },
                "darwin_prompt_hardcoded": "June 7-15 (:15704 literal)",
                "prompt_has_disclaimer": "NO — disclaimer lives only in dead buildSystemPrompt (:15375)",
                "hardcoded_contradictions": [
                  "$50,000 deposit target (:15691) vs \"$3k currently\" (:15715)",
                  "Salary $117,500 (:15698)",
                  "$68k total (:15740)",
                  "KIA/Firstmac by name (:15693)"
                ]
              },
              "error": null
            }
          ]
        }
      },
      "openBug": null,
      "links": []
    },
    {
      "id": "SLY-4",
      "type": "bug",
      "caseId": "hero-render-drift",
      "title": "Dashboard headline number visibly drifts across renders",
      "surface": "dash",
      "group": "dashboard",
      "severity": "P1",
      "kind": "candidate",
      "summary": "After a single log, the big balance on the dashboard was seen showing three different values across consecutive frames ($2,045 → $1,914 → $1,782) — the headline appears to move on its own. The state underneath is correct (the ledger shows a clean change); it's the on-screen number that wobbles.",
      "rich": {
        "mechanism": "Most likely the animated “counter roll” (the number tweening to its new value) caught mid-animation by the screenshot — the walker's CSS freeze stops CSS animations but not a JS requestAnimationFrame counter. The alternative is a genuine render-vs-state divergence. Needs a walk with the counter settled before capture to tell which.",
        "rootCause": "Unconfirmed — candidate. Either a rAF counter-roll caught mid-tween (display-layer, benign) or a render path reading a pre-settle value (would be a real display bug). Do NOT promote until re-walked with the counter stable.",
        "fix": "Add a counter-settle wait to the walker (poll the rendered number until stable before screenshot), re-walk, and compare to the clean S.bal. If it still drifts with the counter settled, trace the hero render path.",
        "files": [
          "walker: settle the hero counter before screenshot",
          "dashboard hero render path (TBD on confirm)"
        ],
        "evidence": {
          "flow": "log-transaction",
          "walkDir": "2026-05-26T09-00-07",
          "steps": [
            {
              "step": "baseline",
              "action": "Dashboard",
              "lands": [],
              "delta": {},
              "probe": null,
              "error": null
            },
            {
              "step": "open-quicklog",
              "action": "Open Quick Log",
              "lands": [],
              "delta": {},
              "probe": null,
              "error": null
            },
            {
              "step": "select-expense",
              "action": "Select 'Expense' type",
              "lands": [],
              "delta": {},
              "probe": null,
              "error": null
            },
            {
              "step": "enter",
              "action": "Enter $4.50 + note",
              "lands": [],
              "delta": {},
              "probe": null,
              "error": null
            },
            {
              "step": "submit",
              "action": "Submit (quickLogTxn)",
              "lands": [
                "txn_record",
                "balance_apply_delta",
                "txn_record",
                "balance_apply_delta",
                "bucket_saved_change"
              ],
              "delta": {
                "bal": "4800 → 4795",
                "txns.length": "9 → 11",
                "bucket:China Holiday": "1500 → 1500.5"
              },
              "probe": null,
              "error": null
            },
            {
              "step": "aftermath",
              "action": "Dashboard after",
              "lands": [],
              "delta": {},
              "probe": null,
              "error": null
            }
          ]
        }
      },
      "openBug": 13,
      "links": [
        {
          "to": "SLY-6",
          "why": "same surface (dash)"
        },
        {
          "to": "OPEN-BUGS #13",
          "why": "canonical bug record"
        }
      ]
    },
    {
      "id": "SLY-5",
      "type": "bug",
      "caseId": "no-commit-feedback",
      "title": "Lock / unlock / undo give no visible confirmation",
      "surface": "plan",
      "group": "plan",
      "severity": "P1",
      "kind": "candidate",
      "summary": "State-changing actions — locking a plan, unlocking it, undoing a bill — produced screens that are pixel-identical before and after. For a money app, an action that changes something with no visible “it happened” is a trust gap: you can't tell if it worked.",
      "rich": {
        "mechanism": "The lock/unlock loop (6 frames) and the bill undo (3 frames) render no badge, frozen field, or toast that distinguishes the new state from the old.",
        "rootCause": "UX finding (Layer-C). The state changes correctly (audit lands confirm lock/unlock fired) but the UI gives no feedback signal.",
        "fix": "Add a lock badge + frozen-field styling when a plan is locked; an explicit toast/confirmation on undo; a visible state marker on unlock. Pair with the bills-undo fix (which currently no-ops anyway).",
        "files": [
          "plan canvas lock/unlock render",
          "bill undo render"
        ],
        "evidence": {
          "flow": "plan-lock",
          "walkDir": "2026-05-26T09-00-07",
          "steps": [
            {
              "step": "open-plan",
              "action": "Open Payday canvas",
              "lands": [],
              "delta": {},
              "probe": null,
              "error": null
            },
            {
              "step": "set-override",
              "action": "Set Rainy Day override $100 (BRAIN.plan.setOverride)",
              "lands": [
                "plan_override_set"
              ],
              "delta": {},
              "probe": null,
              "error": null
            },
            {
              "step": "lock",
              "action": "Lock plan (BRAIN.plan.lock)",
              "lands": [
                "payday_plan_locked",
                "payday_plan_locked"
              ],
              "delta": {
                "activePlan.lockedAt": "null → 1779753610149"
              },
              "probe": null,
              "error": null
            },
            {
              "step": "probe-locked",
              "action": "Probe lock-state across 3 stores",
              "lands": [],
              "delta": {},
              "probe": {
                "activePlan_lockedAt": 1779753610149,
                "brain_isLocked_getter": true,
                "localStorage_lockKeys": {
                  "slyght_payday_plan": "{\"lockedAt\":1779753610149,\"lockedSnapshot\":{\"cycleId\":\"2026-"
                },
                "legacy_planLocked": "<none>"
              },
              "error": null
            },
            {
              "step": "unlock",
              "action": "Unlock plan",
              "lands": [
                "payday_plan_unlocked",
                "payday_plan_unlocked"
              ],
              "delta": {
                "activePlan.lockedAt": "1779753610149 → null"
              },
              "probe": null,
              "error": null
            },
            {
              "step": "probe-unlocked",
              "action": "Probe lock-state after unlock",
              "lands": [],
              "delta": {},
              "probe": {
                "activePlan_lockedAt": null,
                "brain_isLocked_getter": false,
                "localStorage_lockKeys": {
                  "slyght_payday_plan": "{\"lockedAt\":null,\"lockedSnapshot\":null}"
                },
                "legacy_planLocked": "<none>"
              },
              "error": null
            }
          ]
        }
      },
      "openBug": null,
      "links": [
        {
          "to": "SLY-7",
          "why": "same surface (plan)"
        }
      ]
    },
    {
      "id": "SLY-6",
      "type": "bug",
      "caseId": "legibility-debt",
      "title": "Low-contrast + malformed money lines on the surfaces that must be trusted",
      "surface": "dash",
      "group": "dashboard",
      "severity": "P1",
      "kind": "candidate",
      "summary": "Some of the exact lines that justify the headline numbers are hard to read or broken: grey-on-grey calendar bill amounts, “debug-look” multi-colour monospace math lines, and a malformed “$#0” in the canvas reconciliation line (“WHERE THE $5,000 SITS NOW”). The justifications for your money should be the most legible thing, not the least.",
      "rich": {
        "mechanism": "Decorative low-contrast text used where primary numbers belong; a formatting bug producing `$#0` in the canvas reconciliation string.",
        "rootCause": "UX finding (Layer-C) + a string-format bug for the `$#0` line.",
        "fix": "Lift money figures to high-contrast (white) with secondary labels; fix the `$#0` format bug in the canvas reconciliation line. Cross-ref the slyght contrast rule (numbers always --text).",
        "files": [
          "canvas reconciliation line ($#0 format bug)",
          "calendar bill-amount styling"
        ],
        "evidence": null
      },
      "openBug": null,
      "links": [
        {
          "to": "SLY-4",
          "why": "same surface (dash)"
        }
      ]
    },
    {
      "id": "SLY-7",
      "type": "bug",
      "caseId": "plan-lock-legacy-path",
      "title": "Plan lock-state: only the canonical unlock path is proven clean",
      "surface": "plan",
      "group": "plan",
      "severity": "P2",
      "kind": "candidate",
      "summary": "Locking and unlocking a plan through the main (canonical) path leaves all three places that track “is it locked?” agreeing. But there's a second, older unlock path (used by some UI) that wasn't exercised — and history says the two paths clear different subsets of those three stores, which can leave a stale lock.",
      "rich": {
        "mechanism": "Lock-state lives in three stores (activePlan.lockedAt + a localStorage key + a BRAIN getter). The canonical unlock clears all three; a legacy/UI unlock path historically clears only some.",
        "rootCause": "Not yet walked — candidate. The canonical path is verified clean (probe shows all three cleared); the legacy path is unexercised (ADR Bundle 32.7 territory).",
        "fix": "Walk the legacy/UI unlock path; if it leaves a stale store, consolidate to a single unlock that clears all three (or one source of truth).",
        "files": [
          "BRAIN.plan.unlock (canonical — clean)",
          "legacy/UI unlock path (unwalked)"
        ],
        "evidence": {
          "flow": "plan-lock",
          "walkDir": "2026-05-26T09-00-07",
          "steps": [
            {
              "step": "open-plan",
              "action": "Open Payday canvas",
              "lands": [],
              "delta": {},
              "probe": null,
              "error": null
            },
            {
              "step": "set-override",
              "action": "Set Rainy Day override $100 (BRAIN.plan.setOverride)",
              "lands": [
                "plan_override_set"
              ],
              "delta": {},
              "probe": null,
              "error": null
            },
            {
              "step": "lock",
              "action": "Lock plan (BRAIN.plan.lock)",
              "lands": [
                "payday_plan_locked",
                "payday_plan_locked"
              ],
              "delta": {
                "activePlan.lockedAt": "null → 1779753610149"
              },
              "probe": null,
              "error": null
            },
            {
              "step": "probe-locked",
              "action": "Probe lock-state across 3 stores",
              "lands": [],
              "delta": {},
              "probe": {
                "activePlan_lockedAt": 1779753610149,
                "brain_isLocked_getter": true,
                "localStorage_lockKeys": {
                  "slyght_payday_plan": "{\"lockedAt\":1779753610149,\"lockedSnapshot\":{\"cycleId\":\"2026-"
                },
                "legacy_planLocked": "<none>"
              },
              "error": null
            },
            {
              "step": "unlock",
              "action": "Unlock plan",
              "lands": [
                "payday_plan_unlocked",
                "payday_plan_unlocked"
              ],
              "delta": {
                "activePlan.lockedAt": "1779753610149 → null"
              },
              "probe": null,
              "error": null
            },
            {
              "step": "probe-unlocked",
              "action": "Probe lock-state after unlock",
              "lands": [],
              "delta": {},
              "probe": {
                "activePlan_lockedAt": null,
                "brain_isLocked_getter": false,
                "localStorage_lockKeys": {
                  "slyght_payday_plan": "{\"lockedAt\":null,\"lockedSnapshot\":null}"
                },
                "legacy_planLocked": "<none>"
              },
              "error": null
            }
          ]
        }
      },
      "openBug": null,
      "links": [
        {
          "to": "SLY-5",
          "why": "same surface (plan)"
        }
      ]
    },
    {
      "id": "SLY-8",
      "type": "bug",
      "caseId": "bug-3",
      "title": "Round-up cents display in Recent Spending — post-Bundle A retest",
      "surface": null,
      "group": "tracked",
      "severity": "P2",
      "kind": "tracked",
      "summary": "Round-up txns showed as `-$0` in Recent Spending. Bundle A",
      "rich": {
        "mechanism": "",
        "rootCause": "Canonical record in OPEN-BUGS.md #3 — not yet walked for depth.",
        "fix": "Walk this surface to produce a deep case, or scope from the OPEN-BUGS entry.",
        "files": [
          "OPEN-BUGS.md #3"
        ],
        "evidence": null
      },
      "openBug": 3,
      "links": [
        {
          "to": "OPEN-BUGS #3",
          "why": "canonical bug record"
        }
      ]
    },
    {
      "id": "SLY-9",
      "type": "bug",
      "caseId": "bug-5",
      "title": "Auto-sort dialog — verify apply + persist",
      "surface": null,
      "group": "tracked",
      "severity": "P2",
      "kind": "tracked",
      "summary": "Auto-sort dialog opens (per Image 1) but unverified whether",
      "rich": {
        "mechanism": "",
        "rootCause": "Canonical record in OPEN-BUGS.md #5 — not yet walked for depth.",
        "fix": "Walk this surface to produce a deep case, or scope from the OPEN-BUGS entry.",
        "files": [
          "OPEN-BUGS.md #5"
        ],
        "evidence": null
      },
      "openBug": 5,
      "links": [
        {
          "to": "OPEN-BUGS #5",
          "why": "canonical bug record"
        }
      ]
    },
    {
      "id": "SLY-10",
      "type": "bug",
      "caseId": "bug-7",
      "title": "renderCutSliders compares all-time spend to monthly baseline",
      "surface": null,
      "group": "tracked",
      "severity": "P2",
      "kind": "tracked",
      "summary": "`renderCutSliders` uses all-time txn history but compares to",
      "rich": {
        "mechanism": "",
        "rootCause": "Canonical record in OPEN-BUGS.md #7 — not yet walked for depth.",
        "fix": "Walk this surface to produce a deep case, or scope from the OPEN-BUGS entry.",
        "files": [
          "OPEN-BUGS.md #7"
        ],
        "evidence": null
      },
      "openBug": 7,
      "links": [
        {
          "to": "OPEN-BUGS #7",
          "why": "canonical bug record"
        }
      ]
    },
    {
      "id": "SLY-11",
      "type": "bug",
      "caseId": "bug-8",
      "title": "Dashboard \"Running over/under pace this week\" uses lax filter",
      "surface": null,
      "group": "tracked",
      "severity": "P2",
      "kind": "tracked",
      "summary": "Dashboard pace tile (~`:3174`) computes",
      "rich": {
        "mechanism": "",
        "rootCause": "Canonical record in OPEN-BUGS.md #8 — not yet walked for depth.",
        "fix": "Walk this surface to produce a deep case, or scope from the OPEN-BUGS entry.",
        "files": [
          "OPEN-BUGS.md #8"
        ],
        "evidence": null
      },
      "openBug": 8,
      "links": [
        {
          "to": "OPEN-BUGS #8",
          "why": "canonical bug record"
        }
      ]
    },
    {
      "id": "SLY-12",
      "type": "bug",
      "caseId": "bug-17",
      "title": "Cross-tile \"today's spend\" coherence — three renderers, three different values",
      "surface": null,
      "group": "tracked",
      "severity": "P2",
      "kind": "tracked",
      "summary": "Footer persistent strip, dashboard \"Over by $X today\" alert,",
      "rich": {
        "mechanism": "",
        "rootCause": "Canonical record in OPEN-BUGS.md #17 — not yet walked for depth.",
        "fix": "Walk this surface to produce a deep case, or scope from the OPEN-BUGS entry.",
        "files": [
          "OPEN-BUGS.md #17"
        ],
        "evidence": null
      },
      "openBug": 17,
      "links": [
        {
          "to": "OPEN-BUGS #17",
          "why": "canonical bug record"
        }
      ]
    },
    {
      "id": "SLY-13",
      "type": "bug",
      "caseId": "bug-15",
      "title": "Three different daily-cost figures across forecast tiles",
      "surface": null,
      "group": "tracked",
      "severity": "P2",
      "kind": "tracked",
      "summary": "Survival/forecast section presents three different daily",
      "rich": {
        "mechanism": "",
        "rootCause": "Canonical record in OPEN-BUGS.md #15 — not yet walked for depth.",
        "fix": "Walk this surface to produce a deep case, or scope from the OPEN-BUGS entry.",
        "files": [
          "OPEN-BUGS.md #15"
        ],
        "evidence": null
      },
      "openBug": 15,
      "links": [
        {
          "to": "OPEN-BUGS #15",
          "why": "canonical bug record"
        }
      ]
    },
    {
      "id": "SLY-14",
      "type": "bug",
      "caseId": "bug-16",
      "title": "Emergency fund \"saved\" sums travel-goal buckets too",
      "surface": null,
      "group": "tracked",
      "severity": "P2",
      "kind": "tracked",
      "summary": "Emergency fund tile shows \"saved\" amount that includes",
      "rich": {
        "mechanism": "",
        "rootCause": "Canonical record in OPEN-BUGS.md #16 — not yet walked for depth.",
        "fix": "Walk this surface to produce a deep case, or scope from the OPEN-BUGS entry.",
        "files": [
          "OPEN-BUGS.md #16"
        ],
        "evidence": null
      },
      "openBug": 16,
      "links": [
        {
          "to": "OPEN-BUGS #16",
          "why": "canonical bug record"
        }
      ]
    },
    {
      "id": "SLY-15",
      "type": "bug",
      "caseId": "bug-20",
      "title": "Calendar not showing immediate debts on their due dates",
      "surface": null,
      "group": "tracked",
      "severity": "P2",
      "kind": "tracked",
      "summary": "Calendar view does not render markers for immediate-debt",
      "rich": {
        "mechanism": "",
        "rootCause": "Canonical record in OPEN-BUGS.md #20 — not yet walked for depth.",
        "fix": "Walk this surface to produce a deep case, or scope from the OPEN-BUGS entry.",
        "files": [
          "OPEN-BUGS.md #20"
        ],
        "evidence": null
      },
      "openBug": 20,
      "links": [
        {
          "to": "OPEN-BUGS #20",
          "why": "canonical bug record"
        }
      ]
    },
    {
      "id": "SLY-16",
      "type": "bug",
      "caseId": "bug-22",
      "title": "Parallel implementation: 12+ inline `daysLeft(S.payday)` call sites",
      "surface": null,
      "group": "tracked",
      "severity": "P2",
      "kind": "tracked",
      "summary": "`daysLeft(S.payday)` and `MODEL.daysToPayday` are two",
      "rich": {
        "mechanism": "",
        "rootCause": "Canonical record in OPEN-BUGS.md #22 — not yet walked for depth.",
        "fix": "Walk this surface to produce a deep case, or scope from the OPEN-BUGS entry.",
        "files": [
          "OPEN-BUGS.md #22"
        ],
        "evidence": null
      },
      "openBug": 22,
      "links": [
        {
          "to": "OPEN-BUGS #22",
          "why": "canonical bug record"
        }
      ]
    },
    {
      "id": "SLY-17",
      "type": "bug",
      "caseId": "bug-30",
      "title": "Gate verification reliability concern (Mission F finding)",
      "surface": null,
      "group": "tracked",
      "severity": "P2",
      "kind": "tracked",
      "summary": "Mission EXPORT (commit bb30b86) reported \"all gates green\"",
      "rich": {
        "mechanism": "",
        "rootCause": "Canonical record in OPEN-BUGS.md #30 — not yet walked for depth.",
        "fix": "Walk this surface to produce a deep case, or scope from the OPEN-BUGS entry.",
        "files": [
          "OPEN-BUGS.md #30"
        ],
        "evidence": null
      },
      "openBug": 30,
      "links": [
        {
          "to": "OPEN-BUGS #30",
          "why": "canonical bug record"
        }
      ]
    },
    {
      "id": "SLY-18",
      "type": "bug",
      "caseId": "bug-31",
      "title": "paydayDate parallel implementation pattern (second instance)",
      "surface": null,
      "group": "tracked",
      "severity": "P2",
      "kind": "tracked",
      "summary": "Mission F caught the `daysLeft(...)` parallel-impl pattern",
      "rich": {
        "mechanism": "",
        "rootCause": "Canonical record in OPEN-BUGS.md #31 — not yet walked for depth.",
        "fix": "Walk this surface to produce a deep case, or scope from the OPEN-BUGS entry.",
        "files": [
          "OPEN-BUGS.md #31"
        ],
        "evidence": null
      },
      "openBug": 31,
      "links": [
        {
          "to": "OPEN-BUGS #31",
          "why": "canonical bug record"
        }
      ]
    },
    {
      "id": "SLY-19",
      "type": "bug",
      "caseId": "bug-32",
      "title": "Migration auto-delete pattern lacks user-visible surfacing",
      "surface": null,
      "group": "tracked",
      "severity": "P2",
      "kind": "tracked",
      "summary": "Schema-cleanup migrations (`_billsCleanedV1` at L1271-1272,",
      "rich": {
        "mechanism": "",
        "rootCause": "Canonical record in OPEN-BUGS.md #32 — not yet walked for depth.",
        "fix": "Walk this surface to produce a deep case, or scope from the OPEN-BUGS entry.",
        "files": [
          "OPEN-BUGS.md #32"
        ],
        "evidence": null
      },
      "openBug": 32,
      "links": [
        {
          "to": "OPEN-BUGS #32",
          "why": "canonical bug record"
        }
      ]
    },
    {
      "id": "SLY-20",
      "type": "bug",
      "caseId": "bug-33",
      "title": "Mission V fullPage screenshot truncation — Layer V coverage gap",
      "surface": null,
      "group": "tracked",
      "severity": "P2",
      "kind": "tracked",
      "summary": "Playwright `fullPage: true` screenshots are capping at the",
      "rich": {
        "mechanism": "",
        "rootCause": "Canonical record in OPEN-BUGS.md #33 — not yet walked for depth.",
        "fix": "Walk this surface to produce a deep case, or scope from the OPEN-BUGS entry.",
        "files": [
          "OPEN-BUGS.md #33"
        ],
        "evidence": null
      },
      "openBug": 33,
      "links": [
        {
          "to": "OPEN-BUGS #33",
          "why": "canonical bug record"
        }
      ]
    },
    {
      "id": "SLY-21",
      "type": "bug",
      "caseId": "bug-34",
      "title": "Mission E2: dashboard mode-classifier + threshold + filter audit",
      "surface": null,
      "group": "tracked",
      "severity": "P2",
      "kind": "tracked",
      "summary": "Mission E (commit pending) resolved the visible card",
      "rich": {
        "mechanism": "",
        "rootCause": "Canonical record in OPEN-BUGS.md #34 — not yet walked for depth.",
        "fix": "Walk this surface to produce a deep case, or scope from the OPEN-BUGS entry.",
        "files": [
          "OPEN-BUGS.md #34"
        ],
        "evidence": null
      },
      "openBug": 34,
      "links": [
        {
          "to": "OPEN-BUGS #34",
          "why": "canonical bug record"
        }
      ]
    },
    {
      "id": "SLY-22",
      "type": "bug",
      "caseId": "bug-35",
      "title": "Mission V2: Layer 2 render-coherence invariants",
      "surface": null,
      "group": "tracked",
      "severity": "P2",
      "kind": "tracked",
      "summary": "Layer V (visual regression) catches pixel changes but",
      "rich": {
        "mechanism": "",
        "rootCause": "Canonical record in OPEN-BUGS.md #35 — not yet walked for depth.",
        "fix": "Walk this surface to produce a deep case, or scope from the OPEN-BUGS entry.",
        "files": [
          "OPEN-BUGS.md #35"
        ],
        "evidence": null
      },
      "openBug": 35,
      "links": [
        {
          "to": "OPEN-BUGS #35",
          "why": "canonical bug record"
        }
      ]
    },
    {
      "id": "SLY-23",
      "type": "bug",
      "caseId": "bug-36",
      "title": "Mission V3: AI-vision review of baselines",
      "surface": null,
      "group": "tracked",
      "severity": "P2",
      "kind": "tracked",
      "summary": "(see OPEN-BUGS.md #36)",
      "rich": {
        "mechanism": "",
        "rootCause": "Canonical record in OPEN-BUGS.md #36 — not yet walked for depth.",
        "fix": "Walk this surface to produce a deep case, or scope from the OPEN-BUGS entry.",
        "files": [
          "OPEN-BUGS.md #36"
        ],
        "evidence": null
      },
      "openBug": 36,
      "links": [
        {
          "to": "OPEN-BUGS #36",
          "why": "canonical bug record"
        }
      ]
    },
    {
      "id": "SLY-24",
      "type": "bug",
      "caseId": "bug-10",
      "title": "Test-source drift — canonical helpers copy-pasted in tests",
      "surface": null,
      "group": "tracked",
      "severity": "P2",
      "kind": "tracked",
      "summary": "`tests/core.test.js` lines 117–530 copy-paste the bodies",
      "rich": {
        "mechanism": "",
        "rootCause": "Canonical record in OPEN-BUGS.md #10 — not yet walked for depth.",
        "fix": "Walk this surface to produce a deep case, or scope from the OPEN-BUGS entry.",
        "files": [
          "OPEN-BUGS.md #10"
        ],
        "evidence": null
      },
      "openBug": 10,
      "links": [
        {
          "to": "OPEN-BUGS #10",
          "why": "canonical bug record"
        }
      ]
    },
    {
      "id": "SLY-25",
      "type": "bug",
      "caseId": "bug-44",
      "title": "Multi-delete workflow friction — must re-engage delete affordance per txn",
      "surface": null,
      "group": "tracked",
      "severity": "P2",
      "kind": "tracked",
      "summary": "After deleting one txn, deleting a second txn requires a fresh long-press/tap on its delete affordance rather than continuing in a 'delete mode'. The behavior is SAFE (no cascade-delete risk per #43's two-layer defence) but creates friction when the user wants to clean up multipl",
      "rich": {
        "mechanism": "",
        "rootCause": "Canonical record in OPEN-BUGS.md #44 — not yet walked for depth.",
        "fix": "Walk this surface to produce a deep case, or scope from the OPEN-BUGS entry.",
        "files": [
          "OPEN-BUGS.md #44"
        ],
        "evidence": null
      },
      "openBug": 44,
      "links": [
        {
          "to": "OPEN-BUGS #44",
          "why": "canonical bug record"
        }
      ]
    },
    {
      "id": "SLY-26",
      "type": "bug",
      "caseId": "settings-reset-unrecoverable",
      "title": "Reset is unrecoverable — the undo backup is deleted by the reset itself",
      "surface": "settings",
      "group": "settings",
      "severity": "P0",
      "kind": "confirmed",
      "summary": "If you hit Reset there's no getting your data back — the 'undo' backup is stored inside the very blob the reset wipes, so the reset destroys its own safety net. And the warning screen says it'll delete your snapshots, but the code never actually removes them — the copy doesn't match what happens.",
      "rich": {
        "mechanism": "saveUndoState() stashes the backup into S._prevState. S lives in localStorage 'slyght_v5'. _executeReset deletes slyght_v5 (+ seed flags + api key) then reloads — so the backup is gone before undoLastAction could ever read it. Separately, the Stage-2 screen lists 'Snapshots: N' as about to be lost, but _executeReset never touches the slyght_snapshots key.",
        "rootCause": "saveUndoState writes the backup to S._prevState (index.html:15276), which lives inside slyght_v5 — the exact key _executeReset deletes (index.html:14937-14944). No SNAPSHOTS.take before the wipe; the restore path (index.html:15315) has nothing to read. Stage-2 copy (index.html:14899-14900) overstates the deletion.",
        "fix": "Before the wipe, copy the backup OUT of slyght_v5 (use SNAPSHOTS.take or a separate key the reset preserves) so undo has something to restore. Fix the Stage-2 copy to match what _executeReset actually deletes (or delete snapshots if that's intended).",
        "files": [
          "index.html:15276 (saveUndoState → S._prevState)",
          "index.html:14937-14944 (_executeReset deletes slyght_v5)",
          "index.html:14899-14900 (Stage-2 copy overstates)",
          "index.html:15315 (restore — nothing to read)"
        ],
        "evidence": null
      },
      "openBug": null,
      "links": []
    },
    {
      "id": "SLY-27",
      "type": "bug",
      "caseId": "debts-no-partial-paydown",
      "title": "Debts: no partial pay-down (only full clear) + card/canvas total drift (FR-07)",
      "surface": "debts",
      "group": "debts",
      "severity": "P1",
      "kind": "confirmed",
      "summary": "You can only mark a debt fully cleared — there's no way to log a partial payment toward one. And the debt total on the Debts card can disagree with the figure on the Payday canvas, so you see two different 'what I owe' numbers.",
      "rich": {
        "mechanism": "The only pay action is markDebtPaid (full clear via BRAIN.debts.markPaid) — there's no payDownDebt/reduceDebt anywhere. Separately the Debts card headline sums all non-viaRent debts, while the canvas reader getActiveDebtsDueBeforePayday only counts debts with a delayDate inside the cycle — two readers, they drift (FR-07).",
        "rootCause": "No partial-payment writer exists. FR-07 dual-reader divergence: card total index.html:7857-7859 vs canvas reader getActiveDebtsDueBeforePayday index.html:3605-3632 (violates INV-11/INV-18).",
        "fix": "Add a partial pay-down path (log a Debt-repayment txn that reduces debt.amt without clearing it). Converge the two debt-total readers onto one canonical figure.",
        "files": [
          "index.html:8206 (markDebtPaid — full clear only, no partial path)",
          "index.html:7857-7859 (card total reader)",
          "index.html:3605-3632 (canvas reader — drifts)"
        ],
        "evidence": null
      },
      "openBug": null,
      "links": []
    },
    {
      "id": "SLY-28",
      "type": "bug",
      "caseId": "nav-pin-gate-orphaned",
      "title": "PIN gate orphaned — a set PIN does not actually lock the app",
      "surface": "nav",
      "group": "nav",
      "severity": "P1",
      "kind": "confirmed",
      "summary": "Setting a PIN doesn't actually lock anything. When the app opens, nothing checks the PIN or shows the PIN screen — so anyone who opens it is straight in. The lock exists in Settings but the front door never asks for it.",
      "rich": {
        "mechanism": "splashTap() routes to onboarding or straight to the app but never checks S.pinHash and never shows #pin-screen. The pieces exist (verifyPIN, pinKey) but are unreachable on boot — the only references to #pin-screen are HIDE calls.",
        "rootCause": "splashTap (index.html:19917-19924) has no PIN branch; #pin-screen (index.html:828) is only ever hidden (index.html:3951, 4157); verifyPIN (index.html:2218) is unreachable on the boot path.",
        "fix": "In the splash/boot path, if S.pinHash is set, show #pin-screen and gate launchApp behind a successful verifyPIN.",
        "files": [
          "index.html:19917-19924 (splashTap — no PIN branch)",
          "index.html:828 (#pin-screen, only hidden)",
          "index.html:2218 (verifyPIN — unreachable on boot)"
        ],
        "evidence": null
      },
      "openBug": null,
      "links": [
        {
          "to": "SLY-29",
          "why": "same surface (nav)"
        }
      ]
    },
    {
      "id": "SLY-29",
      "type": "bug",
      "caseId": "nav-boot-tdz",
      "title": "Boot TDZ — first-paint financial model falls back to a stub",
      "surface": "nav",
      "group": "nav",
      "severity": "P1",
      "kind": "confirmed",
      "summary": "On boot the financial model briefly fails and falls back to a placeholder, because the startup code runs before the BRAIN engine is switched on — so the very first paint can show stub numbers before it settles.",
      "rich": {
        "mechanism": "load() fires before const BRAIN and const PLAN are initialised. computeFinancialModel touches BRAIN/PLAN and throws 'Cannot access BRAIN before initialization'; refreshModel's try/catch swallows it and uses _modelStub for the first paint.",
        "rootCause": "Temporal dead zone: load() runs at index.html:19877, but const BRAIN is declared later at index.html:20294 (PLAN at :26142). The boot call precedes the engine it needs; caught + stubbed at index.html:4937-4942.",
        "fix": "Defer the boot load()/first refreshModel until after BRAIN/PLAN are initialised (move the boot call below the declarations, or guard the model build until the engine exists).",
        "files": [
          "index.html:19877 (load fires early)",
          "index.html:20294 (const BRAIN declared after)",
          "index.html:4937-4942 (stub fallback)"
        ],
        "evidence": null
      },
      "openBug": null,
      "links": [
        {
          "to": "SLY-28",
          "why": "same surface (nav)"
        }
      ]
    }
  ]
}